st_iframe_postmessage/__init__.py
st_iframe_postmessage/example.py
st_iframe_postmessage/frontend/build/asset-manifest.json
st_iframe_postmessage/frontend/build/index.html
st_iframe_postmessage/frontend/build/static/js/main.fb93be28.js
st_iframe_postmessage/frontend/build/static/js/main.fb93be28.js.LICENSE.txt
st_iframe_postmessage/frontend/build/static/js/main.fb93be28.js.map
st_iframe_postmessage-0.1.0.dist-info/LICENSE
st_iframe_postmessage-0.1.0.dist-info/METADATA
st_iframe_postmessage-0.1.0.dist-info/WHEEL
st_iframe_postmessage-0.1.0.dist-info/top_level.txt
st_iframe_postmessage-0.1.0.dist-info/RECORD
