Metadata-Version: 2.1
Name: st-iframe-postmessage
Version: 0.1.0
Summary: Streamlit component to send postMessage to iframe window embedding application
Home-page: https://github.com/mysiar-org/st-iframe-postmessage
Author: Piotr Synowiec
Author-email: psynowiec@gmail.com
License: MIT
Keywords: streamlit,streamlit-component
Requires-Python: >=3.7
License-File: LICENSE
Requires-Dist: streamlit>=0.63
Provides-Extra: devel
Requires-Dist: wheel; extra == "devel"
Requires-Dist: pytest==7.4.0; extra == "devel"
Requires-Dist: playwright==1.39.0; extra == "devel"
Requires-Dist: requests==2.31.0; extra == "devel"
Requires-Dist: pytest-playwright-snapshot==1.0; extra == "devel"
Requires-Dist: pytest-rerunfailures==12.0; extra == "devel"
